{
  "schemaVersion": 1,
  "version": "1.0.0",
  "type": "data_connector",
  "extraData": {
    "disabledPeriodicSync": false,
    "dataSourceConfigUIURI": "https://raw.mynatapp.cc/",
    "initHeight": 600,
    "initWidth": 520
  },
  "protocol": {
    "type": "http",
    "httpProtocol": {
      "uris": [
        {
          "type": "tableMeta",
          "uri": "/kingdee/table_meta"
        },
        {
          "type": "records",
          "uri": "/kingdee/records"
        }
      ]
    }
  }
}